MANIFEST.in
README.rst
setup.py
aliyun_python_sdk_netana.egg-info/PKG-INFO
aliyun_python_sdk_netana.egg-info/SOURCES.txt
aliyun_python_sdk_netana.egg-info/dependency_links.txt
aliyun_python_sdk_netana.egg-info/requires.txt
aliyun_python_sdk_netana.egg-info/top_level.txt
aliyunsdknetana/__init__.py
aliyunsdknetana/request/__init__.py
aliyunsdknetana/request/v20181018/CreateNetworkDiagnosticRequest.py
aliyunsdknetana/request/v20181018/CreateNetworkQuotaRequestRequest.py
aliyunsdknetana/request/v20181018/DescribeDiagnosticConfigRequest.py
aliyunsdknetana/request/v20181018/DescribeIpLocationAndIspRequest.py
aliyunsdknetana/request/v20181018/DescribeIpv6LocationAndIspRequest.py
aliyunsdknetana/request/v20181018/DescribeNetworkAnalyticsDataTransferRequest.py
aliyunsdknetana/request/v20181018/DescribeNetworkAnalyticsLatencyRequest.py
aliyunsdknetana/request/v20181018/DescribeNetworkAnalyticsNetQualityRequest.py
aliyunsdknetana/request/v20181018/DescribeNetworkAnalyticsPacketLossRequest.py
aliyunsdknetana/request/v20181018/DescribeNetworkQuotaRequestResultRequest.py
aliyunsdknetana/request/v20181018/DescribeNetworkQuotasRequest.py
aliyunsdknetana/request/v20181018/__init__.py